auto_unpack/__init__.py
auto_unpack/app.py
auto_unpack/args.py
auto_unpack/cli.py
auto_unpack/config.py
auto_unpack/constant.py
auto_unpack/env.py
auto_unpack/plugin.py
auto_unpack/release.json
auto_unpack/schema.py
auto_unpack/store.py
auto_unpack/plugins/__init__.py
auto_unpack/plugins/archive.py
auto_unpack/plugins/empty.py
auto_unpack/plugins/flat.py
auto_unpack/plugins/log.py
auto_unpack/plugins/remove.py
auto_unpack/plugins/rename.py
auto_unpack/plugins/scan.py
auto_unpack/plugins/template.py
auto_unpack/plugins/transfer.py
auto_unpack/plugins/control/__init__.py
auto_unpack/plugins/control/filter.py
auto_unpack/plugins/control/loop.py
auto_unpack/plugins/control/merge.py
auto_unpack/plugins/control/switch.py
auto_unpack/util/__init__.py
auto_unpack/util/download.py
auto_unpack/util/exec.py
auto_unpack/util/file.py
auto_unpack/util/logging.py
auto_unpack/util/sevenzip/__init__.py
auto_unpack/util/sevenzip/result.py
auto_unpack/util/sevenzip/lib/7-zip.chm
auto_unpack/util/sevenzip/lib/7-zip.chw
auto_unpack/util/sevenzip/lib/History.txt
auto_unpack/util/sevenzip/lib/License.txt
auto_unpack/util/sevenzip/lib/readme.txt
auto_unpack/util/sevenzip/lib/darwin/amd/x64/7zz
auto_unpack/util/sevenzip/lib/darwin/arm/x64/7zz
auto_unpack/util/sevenzip/lib/linux/amd/x64/7zzs
auto_unpack/util/sevenzip/lib/linux/amd/x86/7zzs
auto_unpack/util/sevenzip/lib/linux/arm/x64/7zzs
auto_unpack/util/sevenzip/lib/linux/arm/x86/7zzs
auto_unpack/util/sevenzip/lib/windows/amd/x64/7z.dll
auto_unpack/util/sevenzip/lib/windows/amd/x64/7z.exe
auto_unpack/util/sevenzip/lib/windows/amd/x86/7z.dll
auto_unpack/util/sevenzip/lib/windows/amd/x86/7z.exe
auto_unpack/util/sevenzip/lib/windows/arm/x64/7z.dll
auto_unpack/util/sevenzip/lib/windows/arm/x64/7z.exe
auto_unpack-2.12.0.dist-info/METADATA
auto_unpack-2.12.0.dist-info/WHEEL
auto_unpack-2.12.0.dist-info/entry_points.txt
auto_unpack-2.12.0.dist-info/licenses/LICENSE
auto_unpack-2.12.0.dist-info/RECORD
