Metadata-Version: 2.3
Name: auto_unpack
Version: 2.12.0
Summary: 压缩包自动解压工具，支持多种压缩包格式。通过组合各种插件，编排流程，则可满足日常解压需求。
Project-URL: Homepage, https://github.com/xiaohuohumax/auto-unpack#readme
Project-URL: Source, https://github.com/xiaohuohumax/auto-unpack
Project-URL: Tracker, https://github.com/xiaohuohumax/auto-unpack/issues
Author: xiaohuohumax
License: MIT
Keywords: archive,auto,auto-unpack,compress,flow,plugin,schedule,unpack
Classifier: Development Status :: 4 - Beta
Classifier: Intended Audience :: Developers
Classifier: License :: OSI Approved :: MIT License
Classifier: Programming Language :: Python :: 3
Classifier: Programming Language :: Python :: 3.8
Classifier: Programming Language :: Python :: 3.9
Classifier: Programming Language :: Python :: 3.10
Classifier: Topic :: Software Development :: Libraries :: Python Modules
Classifier: Topic :: System :: Archiving :: Compression
Classifier: Topic :: Utilities
Requires-Python: >=3.8
Requires-Dist: inquirer>=3.3.0
Requires-Dist: pydantic-settings>=2.7.0
Requires-Dist: pydantic>=2.10.4
Requires-Dist: ruamel-yaml>=0.18.6
